{
  "timestamp": "2025-09-20T02:00:23.991Z",
  "profiling": {
    "duration": 300,
    "samples": 30,
    "interval": "10s"
  },
  "statistics": {
    "duration": "300s",
    "sampleCount": 30,
    "heap": {
      "min": 38.97,
      "max": 56.94,
      "avg": 41.66,
      "final": 40.73
    },
    "heapTotal": {
      "min": 40.7,
      "max": 102.78,
      "avg": 45.98,
      "final": 41.92
    },
    "rss": {
      "min": 141.69,
      "max": 195.08,
      "avg": 147,
      "final": 141.78
    },
    "heapPercent": {
      "min": 54.2,
      "max": 97.7,
      "avg": 94.03,
      "final": 97.15
    }
  },
  "issues": [
    "High heap usage detected: 97.7% max"
  ],
  "samples": [
    {
      "timestamp": 1758333323986,
      "uptime": 0,
      "memory": {
        "rss": 191.78,
        "heapTotal": 101.8,
        "heapUsed": 55.17,
        "external": 4.15,
        "arrayBuffers": 0.5
      },
      "percentages": {
        "heapUsed": 54.2,
        "external": 4.08
      },
      "heapStats": {
        "codeAndMetadataSize": 0,
        "bytecodeAndMetadataSize": 0,
        "externalScriptSourceSize": 0
      }
    },
    {
      "timestamp": 1758333333987,
      "uptime": 10,
      "memory": {
        "rss": 195.08,
        "heapTotal": 102.78,
        "heapUsed": 56.94,
        "external": 4.7,
        "arrayBuffers": 1.06
      },
      "percentages": {
        "heapUsed": 55.4,
        "external": 4.58
      },
      "heapStats": {
        "codeAndMetadataSize": 0,
        "bytecodeAndMetadataSize": 0,
        "externalScriptSourceSize": 0
      }
    },
    {
      "timestamp": 1758333343988,
      "uptime": 20,
      "memory": {
        "rss": 146.17,
        "heapTotal": 40.7,
        "heapUsed": 38.97,
        "external": 3.78,
        "arrayBuffers": 0.15
      },
      "percentages": {
        "heapUsed": 95.73,
        "external": 9.28
      },
      "heapStats": {
        "codeAndMetadataSize": 0,
        "bytecodeAndMetadataSize": 0,
        "externalScriptSourceSize": 0
      }
    },
    {
      "timestamp": 1758333353989,
      "uptime": 30,
      "memory": {
        "rss": 148.34,
        "heapTotal": 41.44,
        "heapUsed": 40.11,
        "external": 4.25,
        "arrayBuffers": 0.63
      },
      "percentages": {
        "heapUsed": 96.8,
        "external": 10.26
      },
      "heapStats": {
        "codeAndMetadataSize": 0,
        "bytecodeAndMetadataSize": 0,
        "externalScriptSourceSize": 0
      }
    },
    {
      "timestamp": 1758333363989,
      "uptime": 40,
      "memory": {
        "rss": 148.36,
        "heapTotal": 41.44,
        "heapUsed": 40.13,
        "external": 4.25,
        "arrayBuffers": 0.63
      },
      "percentages": {
        "heapUsed": 96.84,
        "external": 10.27
      },
      "heapStats": {
        "codeAndMetadataSize": 0,
        "bytecodeAndMetadataSize": 0,
        "externalScriptSourceSize": 0
      }
    },
    {
      "timestamp": 1758333373991,
      "uptime": 50,
      "memory": {
        "rss": 149.94,
        "heapTotal": 42.17,
        "heapUsed": 40.65,
        "external": 4.3,
        "arrayBuffers": 0.67
      },
      "percentages": {
        "heapUsed": 96.39,
        "external": 10.19
      },
      "heapStats": {
        "codeAndMetadataSize": 0,
        "bytecodeAndMetadataSize": 0,
        "externalScriptSourceSize": 0
      }
    },
    {
      "timestamp": 1758333383992,
      "uptime": 60,
      "memory": {
        "rss": 149.94,
        "heapTotal": 42.17,
        "heapUsed": 40.72,
        "external": 4.3,
        "arrayBuffers": 0.67
      },
      "percentages": {
        "heapUsed": 96.55,
        "external": 10.19
      },
      "heapStats": {
        "codeAndMetadataSize": 0,
        "bytecodeAndMetadataSize": 0,
        "externalScriptSourceSize": 0
      }
    },
    {
      "timestamp": 1758333393994,
      "uptime": 70,
      "memory": {
        "rss": 149.28,
        "heapTotal": 42.17,
        "heapUsed": 40.75,
        "external": 4.3,
        "arrayBuffers": 0.67
      },
      "percentages": {
        "heapUsed": 96.62,
        "external": 10.19
      },
      "heapStats": {
        "codeAndMetadataSize": 0,
        "bytecodeAndMetadataSize": 0,
        "externalScriptSourceSize": 0
      }
    },
    {
      "timestamp": 1758333403995,
      "uptime": 80,
      "memory": {
        "rss": 149.3,
        "heapTotal": 42.17,
        "heapUsed": 40.8,
        "external": 4.3,
        "arrayBuffers": 0.67
      },
      "percentages": {
        "heapUsed": 96.75,
        "external": 10.19
      },
      "heapStats": {
        "codeAndMetadataSize": 0,
        "bytecodeAndMetadataSize": 0,
        "externalScriptSourceSize": 0
      }
    },
    {
      "timestamp": 1758333413996,
      "uptime": 90,
      "memory": {
        "rss": 146.44,
        "heapTotal": 42.17,
        "heapUsed": 40.86,
        "external": 4.3,
        "arrayBuffers": 0.67
      },
      "percentages": {
        "heapUsed": 96.89,
        "external": 10.2
      },
      "heapStats": {
        "codeAndMetadataSize": 0,
        "bytecodeAndMetadataSize": 0,
        "externalScriptSourceSize": 0
      }
    },
    {
      "timestamp": 1758333423997,
      "uptime": 100,
      "memory": {
        "rss": 141.75,
        "heapTotal": 42.17,
        "heapUsed": 40.91,
        "external": 4.3,
        "arrayBuffers": 0.67
      },
      "percentages": {
        "heapUsed": 97.01,
        "external": 10.2
      },
      "heapStats": {
        "codeAndMetadataSize": 0,
        "bytecodeAndMetadataSize": 0,
        "externalScriptSourceSize": 0
      }
    },
    {
      "timestamp": 1758333433998,
      "uptime": 110,
      "memory": {
        "rss": 141.83,
        "heapTotal": 42.17,
        "heapUsed": 40.94,
        "external": 4.3,
        "arrayBuffers": 0.67
      },
      "percentages": {
        "heapUsed": 97.08,
        "external": 10.2
      },
      "heapStats": {
        "codeAndMetadataSize": 0,
        "bytecodeAndMetadataSize": 0,
        "externalScriptSourceSize": 0
      }
    },
    {
      "timestamp": 1758333443998,
      "uptime": 120,
      "memory": {
        "rss": 141.83,
        "heapTotal": 42.17,
        "heapUsed": 41,
        "external": 4.3,
        "arrayBuffers": 0.67
      },
      "percentages": {
        "heapUsed": 97.21,
        "external": 10.2
      },
      "heapStats": {
        "codeAndMetadataSize": 0,
        "bytecodeAndMetadataSize": 0,
        "externalScriptSourceSize": 0
      }
    },
    {
      "timestamp": 1758333454000,
      "uptime": 130,
      "memory": {
        "rss": 141.83,
        "heapTotal": 42.17,
        "heapUsed": 41.04,
        "external": 4.3,
        "arrayBuffers": 0.68
      },
      "percentages": {
        "heapUsed": 97.31,
        "external": 10.21
      },
      "heapStats": {
        "codeAndMetadataSize": 0,
        "bytecodeAndMetadataSize": 0,
        "externalScriptSourceSize": 0
      }
    },
    {
      "timestamp": 1758333464002,
      "uptime": 140,
      "memory": {
        "rss": 141.83,
        "heapTotal": 42.17,
        "heapUsed": 41.05,
        "external": 4.3,
        "arrayBuffers": 0.68
      },
      "percentages": {
        "heapUsed": 97.35,
        "external": 10.21
      },
      "heapStats": {
        "codeAndMetadataSize": 0,
        "bytecodeAndMetadataSize": 0,
        "externalScriptSourceSize": 0
      }
    },
    {
      "timestamp": 1758333474002,
      "uptime": 150,
      "memory": {
        "rss": 141.84,
        "heapTotal": 42.17,
        "heapUsed": 41.15,
        "external": 4.31,
        "arrayBuffers": 0.68
      },
      "percentages": {
        "heapUsed": 97.57,
        "external": 10.21
      },
      "heapStats": {
        "codeAndMetadataSize": 0,
        "bytecodeAndMetadataSize": 0,
        "externalScriptSourceSize": 0
      }
    },
    {
      "timestamp": 1758333484004,
      "uptime": 160,
      "memory": {
        "rss": 141.86,
        "heapTotal": 42.17,
        "heapUsed": 41.17,
        "external": 4.31,
        "arrayBuffers": 0.68
      },
      "percentages": {
        "heapUsed": 97.61,
        "external": 10.21
      },
      "heapStats": {
        "codeAndMetadataSize": 0,
        "bytecodeAndMetadataSize": 0,
        "externalScriptSourceSize": 0
      }
    },
    {
      "timestamp": 1758333494005,
      "uptime": 170,
      "memory": {
        "rss": 141.89,
        "heapTotal": 42.17,
        "heapUsed": 41.2,
        "external": 4.31,
        "arrayBuffers": 0.68
      },
      "percentages": {
        "heapUsed": 97.7,
        "external": 10.21
      },
      "heapStats": {
        "codeAndMetadataSize": 0,
        "bytecodeAndMetadataSize": 0,
        "externalScriptSourceSize": 0
      }
    },
    {
      "timestamp": 1758333504005,
      "uptime": 180,
      "memory": {
        "rss": 141.69,
        "heapTotal": 41.92,
        "heapUsed": 40.31,
        "external": 3.9,
        "arrayBuffers": 0.27
      },
      "percentages": {
        "heapUsed": 96.16,
        "external": 9.3
      },
      "heapStats": {
        "codeAndMetadataSize": 0,
        "bytecodeAndMetadataSize": 0,
        "externalScriptSourceSize": 0
      }
    },
    {
      "timestamp": 1758333514006,
      "uptime": 190,
      "memory": {
        "rss": 141.69,
        "heapTotal": 41.92,
        "heapUsed": 40.33,
        "external": 3.9,
        "arrayBuffers": 0.27
      },
      "percentages": {
        "heapUsed": 96.21,
        "external": 9.3
      },
      "heapStats": {
        "codeAndMetadataSize": 0,
        "bytecodeAndMetadataSize": 0,
        "externalScriptSourceSize": 0
      }
    },
    {
      "timestamp": 1758333524006,
      "uptime": 200,
      "memory": {
        "rss": 141.7,
        "heapTotal": 41.92,
        "heapUsed": 40.39,
        "external": 3.9,
        "arrayBuffers": 0.27
      },
      "percentages": {
        "heapUsed": 96.35,
        "external": 9.3
      },
      "heapStats": {
        "codeAndMetadataSize": 0,
        "bytecodeAndMetadataSize": 0,
        "externalScriptSourceSize": 0
      }
    },
    {
      "timestamp": 1758333534007,
      "uptime": 210,
      "memory": {
        "rss": 141.72,
        "heapTotal": 41.92,
        "heapUsed": 40.43,
        "external": 3.9,
        "arrayBuffers": 0.27
      },
      "percentages": {
        "heapUsed": 96.45,
        "external": 9.3
      },
      "heapStats": {
        "codeAndMetadataSize": 0,
        "bytecodeAndMetadataSize": 0,
        "externalScriptSourceSize": 0
      }
    },
    {
      "timestamp": 1758333544009,
      "uptime": 220,
      "memory": {
        "rss": 141.72,
        "heapTotal": 41.92,
        "heapUsed": 40.46,
        "external": 3.9,
        "arrayBuffers": 0.27
      },
      "percentages": {
        "heapUsed": 96.5,
        "external": 9.31
      },
      "heapStats": {
        "codeAndMetadataSize": 0,
        "bytecodeAndMetadataSize": 0,
        "externalScriptSourceSize": 0
      }
    },
    {
      "timestamp": 1758333554011,
      "uptime": 230,
      "memory": {
        "rss": 141.72,
        "heapTotal": 41.92,
        "heapUsed": 40.49,
        "external": 3.9,
        "arrayBuffers": 0.27
      },
      "percentages": {
        "heapUsed": 96.58,
        "external": 9.31
      },
      "heapStats": {
        "codeAndMetadataSize": 0,
        "bytecodeAndMetadataSize": 0,
        "externalScriptSourceSize": 0
      }
    },
    {
      "timestamp": 1758333564013,
      "uptime": 240,
      "memory": {
        "rss": 141.72,
        "heapTotal": 41.92,
        "heapUsed": 40.53,
        "external": 3.9,
        "arrayBuffers": 0.27
      },
      "percentages": {
        "heapUsed": 96.68,
        "external": 9.31
      },
      "heapStats": {
        "codeAndMetadataSize": 0,
        "bytecodeAndMetadataSize": 0,
        "externalScriptSourceSize": 0
      }
    },
    {
      "timestamp": 1758333574014,
      "uptime": 250,
      "memory": {
        "rss": 141.72,
        "heapTotal": 41.92,
        "heapUsed": 40.58,
        "external": 3.9,
        "arrayBuffers": 0.28
      },
      "percentages": {
        "heapUsed": 96.79,
        "external": 9.31
      },
      "heapStats": {
        "codeAndMetadataSize": 0,
        "bytecodeAndMetadataSize": 0,
        "externalScriptSourceSize": 0
      }
    },
    {
      "timestamp": 1758333584014,
      "uptime": 260,
      "memory": {
        "rss": 141.72,
        "heapTotal": 41.92,
        "heapUsed": 40.6,
        "external": 3.91,
        "arrayBuffers": 0.28
      },
      "percentages": {
        "heapUsed": 96.85,
        "external": 9.32
      },
      "heapStats": {
        "codeAndMetadataSize": 0,
        "bytecodeAndMetadataSize": 0,
        "externalScriptSourceSize": 0
      }
    },
    {
      "timestamp": 1758333594016,
      "uptime": 270,
      "memory": {
        "rss": 141.72,
        "heapTotal": 41.92,
        "heapUsed": 40.65,
        "external": 3.91,
        "arrayBuffers": 0.28
      },
      "percentages": {
        "heapUsed": 96.97,
        "external": 9.32
      },
      "heapStats": {
        "codeAndMetadataSize": 0,
        "bytecodeAndMetadataSize": 0,
        "externalScriptSourceSize": 0
      }
    },
    {
      "timestamp": 1758333604016,
      "uptime": 280,
      "memory": {
        "rss": 141.73,
        "heapTotal": 41.92,
        "heapUsed": 40.69,
        "external": 3.91,
        "arrayBuffers": 0.28
      },
      "percentages": {
        "heapUsed": 97.07,
        "external": 9.32
      },
      "heapStats": {
        "codeAndMetadataSize": 0,
        "bytecodeAndMetadataSize": 0,
        "externalScriptSourceSize": 0
      }
    },
    {
      "timestamp": 1758333614018,
      "uptime": 290,
      "memory": {
        "rss": 141.78,
        "heapTotal": 41.92,
        "heapUsed": 40.73,
        "external": 3.91,
        "arrayBuffers": 0.28
      },
      "percentages": {
        "heapUsed": 97.15,
        "external": 9.32
      },
      "heapStats": {
        "codeAndMetadataSize": 0,
        "bytecodeAndMetadataSize": 0,
        "externalScriptSourceSize": 0
      }
    }
  ]
}